{"cameraMode":{"drawMode":0,"name":"Shaded","section":"Shading Mode"},"sceneLighting":true,"audioPlay":false,"sceneViewState":{"m_AlwaysRefresh":false,"showFog":true,"showSkybox":true,"showFlares":true,"showImageEffects":true,"showParticleSystems":true,"showVisualEffectGraphs":true,"m_FxEnabled":true},"in2DMode":false,"pivot":{"x":-8.377097129821778,"y":6.211052894592285,"z":-4.466885566711426},"rotation":{"x":-0.233516663312912,"y":-0.017037520185112954,"z":0.0034820809960365297,"w":-0.9718199968338013},"size":5.98069953918457,"orthographic":false}